antpycv/ClassificationModule.py
antpycv/ColorModule.py
antpycv/FPS.py
antpycv/FaceDetectionModule.py
antpycv/FaceMeshModule.py
antpycv/HandTrackingModule.py
antpycv/PIDModule.py
antpycv/PlotModule.py
antpycv/PoseModule.py
antpycv/SelfiSegmentationModule.py
antpycv/SerialModule.py
antpycv/Utils.py
antpycv/__init__.py
antpycv-1.0.1.dist-info/METADATA
antpycv-1.0.1.dist-info/WHEEL
antpycv-1.0.1.dist-info/top_level.txt
antpycv-1.0.1.dist-info/RECORD
